melowrag/__init__.py
melowrag/compression/__init__.py
melowrag/compression/base_compression.py
melowrag/compression/compress.py
melowrag/compression/compression_factory.py
melowrag/compression/tar_compression.py
melowrag/compression/zip_compression.py
melowrag/databases/__init__.py
melowrag/databases/base.py
melowrag/databases/client.py
melowrag/databases/db_encoder/__init__.py
melowrag/databases/db_encoder/base.py
melowrag/databases/db_encoder/factory.py
melowrag/databases/db_encoder/image.py
melowrag/databases/db_encoder/serialize.py
melowrag/databases/db_schema/__init__.py
melowrag/databases/db_schema/orm.py
melowrag/databases/db_schema/statement.py
melowrag/databases/db_sql/__init__.py
melowrag/databases/db_sql/aggregate.py
melowrag/databases/db_sql/base.py
melowrag/databases/db_sql/expression.py
melowrag/databases/db_sql/token.py
melowrag/databases/duckdb.py
melowrag/databases/embedded.py
melowrag/databases/factory.py
melowrag/databases/rdbms.py
melowrag/databases/sqlite.py
melowrag/datatypes/__init__.py
melowrag/datatypes/base.py
melowrag/datatypes/labels.py
melowrag/datatypes/questions.py
melowrag/datatypes/sequences.py
melowrag/datatypes/texts.py
melowrag/datatypes/tokens.py
melowrag/graph_algorithms/__init__.py
melowrag/graph_algorithms/base.py
melowrag/graph_algorithms/factory.py
melowrag/graph_algorithms/networkx.py
melowrag/graph_algorithms/query.py
melowrag/graph_algorithms/rdbms.py
melowrag/graph_algorithms/topics.py
melowrag/modeling/__init__.py
melowrag/modeling/models.py
melowrag/modeling/onnx.py
melowrag/modeling/pooling/__init__.py
melowrag/modeling/pooling/base.py
melowrag/modeling/pooling/cls.py
melowrag/modeling/pooling/factory.py
melowrag/modeling/pooling/mean.py
melowrag/modeling/registry.py
melowrag/modeling/tokendetection.py
melowrag/pipelines/__init__.py
melowrag/pipelines/audio/__init__.py
melowrag/pipelines/audio/audiomixer.py
melowrag/pipelines/audio/audiostream.py
melowrag/pipelines/audio/microphone.py
melowrag-0.0.2.dist-info/LICENSE
melowrag-0.0.2.dist-info/METADATA
melowrag-0.0.2.dist-info/WHEEL
melowrag-0.0.2.dist-info/RECORD
